{
    "$schema": "https://mintlify.com/docs.json",
    "theme": "linden",
    "name": "Waterbus",
    "colors": {
        "primary": "#9B28D0",
        "light": "#FFA8DC",
        "dark": "#9B28D0"
    },
    "favicon": "/favicon.ico",
    "logo": {
        "light": "/logo/logo.png",
        "dark": "/logo/logo.png"
    },
    "navigation": {
        "groups": [
            {
                "group": "CHANGELOG",
                "pages": [
                    "index",
                    "flutter-sdk"
                ]
            }
        ]
    },
    "navbar": {
        "links": []
    },
    "footer": {
        "socials": {
            "github": "https://github.com/waterbustech"
        }
    }
}